reactify/__init__.py
reactify/admin.py
reactify/apps.py
reactify/babel.config.json
reactify/package.json
reactify/tests.py
reactify/urls.py
reactify/views.py
reactify/webpack.config.js
reactify/management/__init__.py
reactify/management/commands/__init__.py
reactify/management/commands/reactify.py
reactify/migrations/__init__.py
reactify/react/index.js
reactify/react/components/App.js
reactify/react/redux/store.js
reactify/react/redux/actions/api.js
reactify/react/redux/actions/types.js
reactify/react/redux/reducers/index.js
reactify/static/main.js
reactify/static/css/bootstrap.min.css
reactify/static/css/styles.css
reactify/static/images/favicon.svg
reactify/static/js/bootstrap.min.js
reactify/templates/base.html
reactify/templates/reactify/index.html
django_reactify-1.4.0.dist-info/LICENSE
django_reactify-1.4.0.dist-info/METADATA
django_reactify-1.4.0.dist-info/WHEEL
django_reactify-1.4.0.dist-info/top_level.txt
django_reactify-1.4.0.dist-info/RECORD
